wtao/__init__.py
wtao/console.py
wtao/lxq/__init__.py
wtao/lxq/fireworks_explosion.py
wtao/resources/__init__.py
wtao/resources/fireworks/__init__.py
wtao/resources/fireworks/icon.png
wtao/resources/fireworks/main.ui
wtao/resources/fireworks/paitou.gif
wtao/resources/fireworks/snow.gif
wtao/resources/fireworks/fireworks/__init__.py
wtao/resources/fireworks/fireworks/firework_1.gif
wtao/resources/fireworks/fireworks/firework_2.gif
wtao/resources/fireworks/fireworks/firework_3.gif
wtao/resources/fireworks/fireworks/firework_5.gif
wtao/resources/fireworks/fireworks/firework_6.gif
wtao/resources/fireworks/fireworks/firework_7.gif
wtao-0.1.1.dist-info/METADATA
wtao-0.1.1.dist-info/WHEEL
wtao-0.1.1.dist-info/entry_points.txt
wtao-0.1.1.dist-info/top_level.txt
wtao-0.1.1.dist-info/RECORD
